bethe/__init__.py
bethe/bethe_ansatz.py
bethe/bethe_equation.py
bethe-0.1.1.dist-info/LICENSE
bethe-0.1.1.dist-info/METADATA
bethe-0.1.1.dist-info/WHEEL
bethe-0.1.1.dist-info/top_level.txt
bethe-0.1.1.dist-info/RECORD
