Metadata-Version: 2.1
Name: bethe
Version: 0.1.1
Summary: Bethe Equation Solver
Home-page: https://github.com/CyberGuy99/bethe
Author: CyberGuy99
Author-email: rushilcd@umd.edu
License-File: LICENSE
Requires-Dist: numpy
Requires-Dist: scipy
